td/__init__.py
td/client.py
td/enums.py
td/exceptions.py
td/message.py
td/oauth.py
td/option_chain.py
td/orders.py
td/stream.py
td/utils.py
td/watchlist_item.py
td/app/auth.py
td/templates/auth.html
td/templates/index.html
schwab_python_api-0.0.2.dist-info/LICENSE
schwab_python_api-0.0.2.dist-info/METADATA
schwab_python_api-0.0.2.dist-info/WHEEL
schwab_python_api-0.0.2.dist-info/top_level.txt
schwab_python_api-0.0.2.dist-info/RECORD
