Metadata-Version: 2.1
Name: schwab-python-api
Version: 0.0.2
Summary: A python client lirbary for the Schwab API.
Home-page: https://github.com/dhonn/schwab-python-api
Author: Dhonn Lushine
Author-email: dhonn@yahoo.com
Keywords: finance,schwab,api
Classifier: Development Status :: 3 - Alpha
Classifier: Intended Audience :: Financial and Insurance Industry
Classifier: License :: OSI Approved :: MIT License
Classifier: Natural Language :: English
Classifier: Operating System :: OS Independent
Classifier: Programming Language :: Python :: 3
Requires-Python: >=3.7
License-File: LICENSE
Requires-Dist: websockets
Requires-Dist: requests
Requires-Dist: flask
Requires-Dist: requests-oauthlib
Requires-Dist: pyopenssl
Requires-Dist: portalocker
Requires-Dist: python-dotenv
